ssc_dsai_pii_removal/__init__.py
ssc_dsai_pii_removal/_version.py
ssc_dsai_pii_removal/ssc_dsai_pii_removal.py
ssc_dsai_pii_removal-0.0.4.dist-info/LICENSE
ssc_dsai_pii_removal-0.0.4.dist-info/METADATA
ssc_dsai_pii_removal-0.0.4.dist-info/WHEEL
ssc_dsai_pii_removal-0.0.4.dist-info/entry_points.txt
ssc_dsai_pii_removal-0.0.4.dist-info/top_level.txt
ssc_dsai_pii_removal-0.0.4.dist-info/RECORD
